soslr/__init__.py
soslr/sos.py
soslr-0.1.2.dist-info/LICENSE
soslr-0.1.2.dist-info/METADATA
soslr-0.1.2.dist-info/WHEEL
soslr-0.1.2.dist-info/top_level.txt
soslr-0.1.2.dist-info/RECORD
