Metadata-Version: 2.1
Name: soslr
Version: 0.1.2
Summary: A semi-supervised learning library using iterative pseudo-labeling.
Home-page: https://github.com/SoroushOskouei/Semi-Supervised-sos
Author: Soroush Oskouei
Classifier: Programming Language :: Python :: 3
Classifier: License :: OSI Approved :: MIT License
Classifier: Operating System :: OS Independent
Classifier: Intended Audience :: Developers
Classifier: Intended Audience :: Science/Research
Classifier: Topic :: Scientific/Engineering :: Artificial Intelligence
Requires-Python: >=3.7
License-File: LICENSE
Requires-Dist: torch (>=1.7)
Requires-Dist: torchvision
Requires-Dist: numpy
Requires-Dist: Pillow
